PyOptCollection-0.0.1.dist-info/DESCRIPTION.rst
PyOptCollection-0.0.1.dist-info/METADATA
PyOptCollection-0.0.1.dist-info/RECORD
PyOptCollection-0.0.1.dist-info/WHEEL
PyOptCollection-0.0.1.dist-info/metadata.json
PyOptCollection-0.0.1.dist-info/top_level.txt
py_opt_collection/__init__.py
py_opt_collection/optimization.py
py_opt_collection/pso.py
py_opt_collection/test_functions.py
py_opt_collection/utils.py
