Metadata-Version: 2.0
Name: PyOptCollection
Version: 0.0.1
Summary: A collection of Optimization Algorithms.
Home-page: UNKNOWN
Author: Nghia Tr. Nguyen
Author-email: nghia@viisix.space
License: UNKNOWN
Platform: UNKNOWN
Classifier: Development Status :: 2 - Pre-Alpha
Classifier: Intended Audience :: Developers
Classifier: Intended Audience :: Education
Classifier: Intended Audience :: Science/Research
Classifier: License :: OSI Approved :: BSD License
Classifier: Programming Language :: Python :: 3.5
Classifier: Programming Language :: Python :: 3.6
Classifier: Topic :: Software Development :: Libraries
